swarmflow/__init__.py
swarmflow/hooks.py
swarmflow/core/__init__.py
swarmflow/core/decorator.py
swarmflow/core/flow.py
swarmflow/core/policy.py
swarmflow/core/pricing.py
swarmflow/core/runner.py
swarmflow/core/task.py
swarmflow/core/telemetry.py
swarmflow/core/utils.py
swarmflow/core/telemetry/__init__.py
swarmflow/core/telemetry/anthropic.py
swarmflow/core/telemetry/base.py
swarmflow/core/telemetry/crewai.py
swarmflow/core/telemetry/groq.py
swarmflow/core/telemetry/langchain.py
swarmflow/core/telemetry/openai.py
swarmflow-0.5.0.dist-info/licenses/LICENSE
swarmflow-0.5.0.dist-info/METADATA
swarmflow-0.5.0.dist-info/WHEEL
swarmflow-0.5.0.dist-info/top_level.txt
swarmflow-0.5.0.dist-info/RECORD
