Metadata-Version: 2.4
Name: swarmflow
Version: 0.5.0
Summary: SwarmFlow: A distributed multi-agent orchestration framework
Home-page: https://github.com/anirame128/swarmflow
Download-URL: https://github.com/anirame128/swarmflow/archive/refs/tags/v0.5.0.tar.gz
Author: Anirudh Ramesh
Author-email: anirudhramesh2021@gmail.com
Maintainer: Anirudh Ramesh
Maintainer-email: anirudhramesh2021@gmail.com
Project-URL: Bug Reports, https://github.com/anirame128/swarmflow/issues
Project-URL: Source, https://github.com/anirame128/swarmflow
Project-URL: Documentation, https://github.com/anirame128/swarmflow#readme
Project-URL: Changelog, https://github.com/anirame128/swarmflow/blob/main/CHANGELOG.md
Keywords: ai,agents,orchestration,workflow,llm,multi-agent,distributed,observability
Classifier: Development Status :: 3 - Alpha
Classifier: Intended Audience :: Developers
Classifier: Intended Audience :: Science/Research
Classifier: License :: OSI Approved :: MIT License
Classifier: Operating System :: OS Independent
Classifier: Programming Language :: Python :: 3
Classifier: Programming Language :: Python :: 3.8
Classifier: Programming Language :: Python :: 3.9
Classifier: Programming Language :: Python :: 3.10
Classifier: Programming Language :: Python :: 3.11
Classifier: Programming Language :: Python :: 3.12
Classifier: Programming Language :: Python :: 3.13
Classifier: Topic :: Software Development :: Libraries :: Python Modules
Classifier: Topic :: Scientific/Engineering :: Artificial Intelligence
Classifier: Topic :: System :: Distributed Computing
Requires-Python: >=3.8
License-File: LICENSE
Requires-Dist: requests>=2.25.0
Requires-Dist: opentelemetry-api>=1.20.0
Requires-Dist: opentelemetry-sdk>=1.20.0
Requires-Dist: python-dotenv>=0.19.0
Dynamic: author
Dynamic: author-email
Dynamic: classifier
Dynamic: description
Dynamic: description-content-type
Dynamic: download-url
Dynamic: home-page
Dynamic: keywords
Dynamic: license-file
Dynamic: maintainer
Dynamic: maintainer-email
Dynamic: project-url
Dynamic: requires-dist
Dynamic: requires-python
Dynamic: summary
